mannhunter/__init__.py
mannhunter/cli.py
mannhunter/core.py
mannhunter/tests/__init__.py
mannhunter/tests/cli.py
mannhunter-0.0.0_dev.dist-info/METADATA
mannhunter-0.0.0_dev.dist-info/entry_points.txt
mannhunter-0.0.0_dev.dist-info/RECORD
mannhunter-0.0.0_dev.dist-info/DESCRIPTION.rst
mannhunter-0.0.0_dev.dist-info/WHEEL
mannhunter-0.0.0_dev.dist-info/top_level.txt
mannhunter-0.0.0_dev.dist-info/metadata.json
