Metadata-Version: 2.0
Name: mannhunter
Version: 0.0.0-dev
Summary: A memory limiting tool for Supervisor
Home-page: https://github.com/borntyping/mannhunter
Author: Sam Clements
Author-email: sam.clements@datasift.com
License: MIT
Platform: UNKNOWN
Classifier: Development Status :: 4 - Beta
Classifier: Environment :: No Input/Output (Daemon)
Classifier: License :: OSI Approved
Classifier: License :: OSI Approved :: MIT License
Classifier: Operating System :: Unix
Classifier: Programming Language :: Python
Classifier: Programming Language :: Python :: 2
Classifier: Programming Language :: Python :: 2.6
Classifier: Programming Language :: Python :: 2.7
Classifier: Topic :: System :: Logging
Classifier: Topic :: System :: Monitoring
Classifier: Topic :: System :: Networking
Classifier: Topic :: System :: Systems Administration
Requires-Dist: click (>=3.1,<4.0)
Requires-Dist: psutil (>=2.1.1,<3.0.0)
Requires-Dist: riemann-client (>=5.0.0,<6.0.0)
Requires-Dist: supervisor (>=3.0,<4.0)
